beaconrunner/__init__.py
beaconrunner/brlib.py
beaconrunner/cadCADsupSUP.py
beaconrunner/eth2.py
beaconrunner/eth2fastspec.py
beaconrunner/network.py
beaconrunner/simulator.py
beaconrunner/specs.py
beaconrunner/validatorlib.py
beaconrunner/utils/__init__.py
beaconrunner/utils/cadCADsupSUP.py
beaconrunner/utils/eth2.py
beaconrunner/validators/ASAPValidator.py
beaconrunner/validators/PrudentValidator.py
beaconrunner/validators/__init__.py
beaconrunner-0.1.3.dist-info/LICENSE
beaconrunner-0.1.3.dist-info/METADATA
beaconrunner-0.1.3.dist-info/WHEEL
beaconrunner-0.1.3.dist-info/top_level.txt
beaconrunner-0.1.3.dist-info/RECORD
