Metadata-Version: 2.1
Name: beaconrunner
Version: 0.1.3
Summary: Agent-based simulation environment for eth2
Home-page: https://github.com/barnabemonnot/beaconrunner
Author: Barnabé Monnot
Author-email: barnabe.monnot@ethereum.org
License: MIT
Platform: UNKNOWN
Requires-Python: >=3.8
Requires-Dist: eth2spec
Requires-Dist: cadCAD
Requires-Dist: pandas
Requires-Dist: milagro-bls-binding
